pc_builder/__init__.py
pc_builder/cli.py
pc_builder/config.py
pc_builder/main.py
pc_builder/compatibility/__init__.py
pc_builder/compatibility/case.py
pc_builder/compatibility/cpu.py
pc_builder/compatibility/cpucooler.py
pc_builder/compatibility/gpu.py
pc_builder/compatibility/hdd.py
pc_builder/compatibility/motherboard.py
pc_builder/compatibility/psu.py
pc_builder/compatibility/ram.py
pc_builder/compatibility/ssd.py
pc_builder/components/__init__.py
pc_builder/components/case.py
pc_builder/components/cpu.py
pc_builder/components/cpucooler.py
pc_builder/components/gpu.py
pc_builder/components/hdd.py
pc_builder/components/motherboard.py
pc_builder/components/psu.py
pc_builder/components/ram.py
pc_builder/components/ssd.py
pc_builder/scripts/__init__.py
pc_builder/scripts/populateJSON.py
pc_builder/suggestions/__init__.py
pc_builder/suggestions/case.py
pc_builder/suggestions/cpu.py
pc_builder/suggestions/cpucooler.py
pc_builder/suggestions/gpu.py
pc_builder/suggestions/hdd.py
pc_builder/suggestions/motherboard.py
pc_builder/suggestions/psu.py
pc_builder/suggestions/ram.py
pc_builder/suggestions/ssd.py
tests/__init__.py
tests/test_case_compatibility.py
tests/test_cpuCooler_compatibility.py
tests/test_cpu_compatibility.py
tests/test_gpu_compatibility.py
tests/test_hdd_compatibility.py
tests/test_motherboard_compatibility.py
tests/test_psu_compatibility.py
tests/test_ram_compatibility.py
tests/test_ssd_compatibility.py
tests/test_suggest_compatible_cases.py
tests/test_suggest_compatible_cpucooler.py
tests/test_suggest_compatible_cpus.py
tests/test_suggest_compatible_gpus.py
tests/test_suggest_compatible_hdd.py
tests/test_suggest_compatible_mb.py
tests/test_suggest_compatible_psus.py
tests/test_suggest_compatible_ram.py
tests/test_suggest_compatible_ssd.py
pc_builder-1.2.6.dist-info/LICENSE
pc_builder-1.2.6.dist-info/METADATA
pc_builder-1.2.6.dist-info/WHEEL
pc_builder-1.2.6.dist-info/entry_points.txt
pc_builder-1.2.6.dist-info/top_level.txt
pc_builder-1.2.6.dist-info/RECORD
