Metadata-Version: 2.1
Name: pc-builder
Version: 1.2.6
Summary: A CLI application for building and managing PC configurations.
Home-page: https://github.com/mif-it-se-2024/group-project-pc-builders
Author: PC Builders Team
Requires-Python: >=3.7
License-File: LICENSE
Requires-Dist: typer
Provides-Extra: dev
Requires-Dist: tox; extra == "dev"
Requires-Dist: pytest; extra == "dev"
Requires-Dist: pyinstaller; extra == "dev"
